{"metadata":{"generated_at":"2025-08-08T10:24:58.463611-04:00","date":"2025-08-08","timezone":"US/Eastern","sport":"baseball_mlb","market":"batter_home_runs","format":"summary","description":"Lightweight summary with game info and player counts","use_case":"Quick overview, mobile apps, initial page loads"},"summary":{"total_games":15,"games_with_props":15,"total_players":701},"games":[{"game_id":"9e5b35ff1456c096421e267b37adc241","away_team":"Cincinnati Reds","home_team":"Pittsburgh Pirates","commence_time":"2025-08-08T18:41:00-04:00","game_time_formatted":"06:41 PM EDT","player_count":50,"odds_status":"unknown","players":[{"player_name":"Andrew McCutchen","line_display":"To Hit HR","sportsbook_count":4},{"player_name":"Andrew McCutchen","line_display":"1.5","sportsbook_count":2},{"player_name":"Andrew McCutchen","line_display":"2.5","sportsbook_count":1},{"player_name":"Austin Hays","line_display":"To Hit HR","sportsbook_count":4},{"player_name":"Austin Hays","line_display":"1.5","sportsbook_count":2},{"player_name":"Austin Hays","line_display":"2.5","sportsbook_count":1},{"player_name":"Bryan Reynolds","line_display":"To Hit HR","sportsbook_count":4},{"player_name":"Bryan Reynolds","line_display":"1.5","sportsbook_count":2},{"player_name":"Bryan Reynolds","line_display":"2.5","sportsbook_count":1},{"player_name":"Elly De La Cruz","line_display":"To Hit HR","sportsbook_count":4},{"player_name":"Elly De La Cruz","line_display":"1.5","sportsbook_count":2},{"player_name":"Elly De La Cruz","line_display":"2.5","sportsbook_count":1},{"player_name":"Gavin Lux","line_display":"To Hit HR","sportsbook_count":4},{"player_name":"Gavin Lux","line_display":"1.5","sportsbook_count":2},{"player_name":"Gavin Lux","line_display":"2.5","sportsbook_count":1},{"player_name":"Henry Davis","line_display":"To Hit HR","sportsbook_count":4},{"player_name":"Henry Davis","line_display":"1.5","sportsbook_count":2},{"player_name":"Henry Davis","line_display":"2.5","sportsbook_count":1},{"player_name":"Isiah Kiner-Falefa","line_display":"To Hit HR","sportsbook_count":3},{"player_name":"Isiah Kiner-Falefa","line_display":"1.5","sportsbook_count":1},{"player_name":"Jared Triolo","line_display":"To Hit HR","sportsbook_count":3},{"player_name":"Jared Triolo","line_display":"1.5","sportsbook_count":1},{"player_name":"Ke'Bryan Hayes","line_display":"To Hit HR","sportsbook_count":3},{"player_name":"Ke'Bryan Hayes","line_display":"1.5","sportsbook_count":1},{"player_name":"Matt McLain","line_display":"To Hit HR","sportsbook_count":4},{"player_name":"Matt McLain","line_display":"1.5","sportsbook_count":2},{"player_name":"Matt McLain","line_display":"2.5","sportsbook_count":1},{"player_name":"Nick Gonzales","line_display":"To Hit HR","sportsbook_count":4},{"player_name":"Nick Gonzales","line_display":"1.5","sportsbook_count":2},{"player_name":"Nick Gonzales","line_display":"2.5","sportsbook_count":1},{"player_name":"Noelvi Marte","line_display":"To Hit HR","sportsbook_count":4},{"player_name":"Noelvi Marte","line_display":"1.5","sportsbook_count":2},{"player_name":"Noelvi Marte","line_display":"2.5","sportsbook_count":1},{"player_name":"Oneil Cruz","line_display":"To Hit HR","sportsbook_count":4},{"player_name":"Oneil Cruz","line_display":"1.5","sportsbook_count":2},{"player_name":"Oneil Cruz","line_display":"2.5","sportsbook_count":1},{"player_name":"Spencer Horwitz","line_display":"To Hit HR","sportsbook_count":4},{"player_name":"Spencer Horwitz","line_display":"1.5","sportsbook_count":2},{"player_name":"Spencer Horwitz","line_display":"2.5","sportsbook_count":1},{"player_name":"Spencer Steer","line_display":"To Hit HR","sportsbook_count":4},{"player_name":"Spencer Steer","line_display":"1.5","sportsbook_count":2},{"player_name":"Spencer Steer","line_display":"2.5","sportsbook_count":1},{"player_name":"TJ Friedl","line_display":"To Hit HR","sportsbook_count":4},{"player_name":"TJ Friedl","line_display":"1.5","sportsbook_count":2},{"player_name":"TJ Friedl","line_display":"2.5","sportsbook_count":1},{"player_name":"Tommy Pham","line_display":"To Hit HR","sportsbook_count":4},{"player_name":"Tommy Pham","line_display":"1.5","sportsbook_count":2},{"player_name":"Tommy Pham","line_display":"2.5","sportsbook_count":1},{"player_name":"Tyler Stephenson","line_display":"To Hit HR","sportsbook_count":3},{"player_name":"Tyler Stephenson","line_display":"1.5","sportsbook_count":1}]},{"game_id":"0a5faa6b463a2f1200ffc1a2a99ede76","away_team":"Oakland Athletics","home_team":"Baltimore Orioles","commence_time":"2025-08-08T19:06:00-04:00","game_time_formatted":"07:06 PM EDT","player_count":42,"odds_status":"unknown","players":[{"player_name":"Adley Rutschman","line_display":"To Hit HR","sportsbook_count":3},{"player_name":"Adley Rutschman","line_display":"1.5","sportsbook_count":1},{"player_name":"Brent Rooker","line_display":"To Hit HR","sportsbook_count":3},{"player_name":"Brent Rooker","line_display":"1.5","sportsbook_count":1},{"player_name":"Brent Rooker","line_display":"2.5","sportsbook_count":1},{"player_name":"Coby Mayo","line_display":"To Hit HR","sportsbook_count":3},{"player_name":"Coby Mayo","line_display":"1.5","sportsbook_count":1},{"player_name":"Colton Cowser","line_display":"To Hit HR","sportsbook_count":3},{"player_name":"Colton Cowser","line_display":"1.5","sportsbook_count":1},{"player_name":"Darell Hernaiz","line_display":"To Hit HR","sportsbook_count":3},{"player_name":"Darell Hernaiz","line_display":"1.5","sportsbook_count":2},{"player_name":"Dylan Carlson","line_display":"To Hit HR","sportsbook_count":3},{"player_name":"Dylan Carlson","line_display":"1.5","sportsbook_count":1},{"player_name":"Gio Urshela","line_display":"To Hit HR","sportsbook_count":3},{"player_name":"Gio Urshela","line_display":"1.5","sportsbook_count":1},{"player_name":"Gunnar Henderson","line_display":"To Hit HR","sportsbook_count":3},{"player_name":"Gunnar Henderson","line_display":"1.5","sportsbook_count":1},{"player_name":"JJ Bleday","line_display":"To Hit HR","sportsbook_count":3},{"player_name":"JJ Bleday","line_display":"1.5","sportsbook_count":1},{"player_name":"JJ Bleday","line_display":"2.5","sportsbook_count":1},{"player_name":"Jackson Holliday","line_display":"To Hit HR","sportsbook_count":3},{"player_name":"Jackson Holliday","line_display":"1.5","sportsbook_count":1},{"player_name":"Jeremiah Jackson","line_display":"To Hit HR","sportsbook_count":3},{"player_name":"Jeremiah Jackson","line_display":"1.5","sportsbook_count":1},{"player_name":"Jordan Westburg","line_display":"To Hit HR","sportsbook_count":3},{"player_name":"Jordan Westburg","line_display":"1.5","sportsbook_count":1},{"player_name":"Lawrence Butler","line_display":"To Hit HR","sportsbook_count":3},{"player_name":"Lawrence Butler","line_display":"1.5","sportsbook_count":2},{"player_name":"Lawrence Butler","line_display":"2.5","sportsbook_count":1},{"player_name":"Max Schuemann","line_display":"To Hit HR","sportsbook_count":3},{"player_name":"Max Schuemann","line_display":"1.5","sportsbook_count":1},{"player_name":"Nick Kurtz","line_display":"To Hit HR","sportsbook_count":3},{"player_name":"Nick Kurtz","line_display":"1.5","sportsbook_count":1},{"player_name":"Nick Kurtz","line_display":"2.5","sportsbook_count":1},{"player_name":"Shea Langeliers","line_display":"To Hit HR","sportsbook_count":3},{"player_name":"Shea Langeliers","line_display":"1.5","sportsbook_count":2},{"player_name":"Tyler O'Neill","line_display":"To Hit HR","sportsbook_count":3},{"player_name":"Tyler O'Neill","line_display":"1.5","sportsbook_count":1},{"player_name":"Tyler O'Neill","line_display":"2.5","sportsbook_count":1},{"player_name":"Tyler Soderstrom","line_display":"To Hit HR","sportsbook_count":3},{"player_name":"Tyler Soderstrom","line_display":"1.5","sportsbook_count":2},{"player_name":"Tyler Soderstrom","line_display":"2.5","sportsbook_count":1}]},{"game_id":"f770b970cc067a640077c4bdb10308f6","away_team":"Houston Astros","home_team":"New York Yankees","commence_time":"2025-08-08T19:06:00-04:00","game_time_formatted":"07:06 PM EDT","player_count":50,"odds_status":"unknown","players":[{"player_name":"Aaron Judge","line_display":"To Hit HR","sportsbook_count":4},{"player_name":"Aaron Judge","line_display":"1.5","sportsbook_count":2},{"player_name":"Aaron Judge","line_display":"2.5","sportsbook_count":1},{"player_name":"Anthony Volpe","line_display":"To Hit HR","sportsbook_count":4},{"player_name":"Anthony Volpe","line_display":"1.5","sportsbook_count":2},{"player_name":"Austin Wells","line_display":"To Hit HR","sportsbook_count":3},{"player_name":"Austin Wells","line_display":"1.5","sportsbook_count":1},{"player_name":"Ben Rice","line_display":"To Hit HR","sportsbook_count":4},{"player_name":"Ben Rice","line_display":"1.5","sportsbook_count":2},{"player_name":"Ben Rice","line_display":"2.5","sportsbook_count":1},{"player_name":"Cam Smith","line_display":"To Hit HR","sportsbook_count":4},{"player_name":"Cam Smith","line_display":"1.5","sportsbook_count":2},{"player_name":"Cam Smith","line_display":"2.5","sportsbook_count":1},{"player_name":"Carlos Correa","line_display":"To Hit HR","sportsbook_count":4},{"player_name":"Carlos Correa","line_display":"1.5","sportsbook_count":2},{"player_name":"Carlos Correa","line_display":"2.5","sportsbook_count":1},{"player_name":"Christian Walker","line_display":"To Hit HR","sportsbook_count":4},{"player_name":"Christian Walker","line_display":"1.5","sportsbook_count":2},{"player_name":"Christian Walker","line_display":"2.5","sportsbook_count":1},{"player_name":"Cody Bellinger","line_display":"To Hit HR","sportsbook_count":4},{"player_name":"Cody Bellinger","line_display":"1.5","sportsbook_count":2},{"player_name":"Cody Bellinger","line_display":"2.5","sportsbook_count":1},{"player_name":"Jasson Domínguez","line_display":"To Hit HR","sportsbook_count":4},{"player_name":"Jasson Domínguez","line_display":"1.5","sportsbook_count":2},{"player_name":"Jasson Domínguez","line_display":"2.5","sportsbook_count":1},{"player_name":"Jazz Chisholm Jr.","line_display":"To Hit HR","sportsbook_count":4},{"player_name":"Jazz Chisholm Jr.","line_display":"1.5","sportsbook_count":2},{"player_name":"Jazz Chisholm Jr.","line_display":"2.5","sportsbook_count":1},{"player_name":"Jeremy Pena","line_display":"To Hit HR","sportsbook_count":4},{"player_name":"Jeremy Pena","line_display":"1.5","sportsbook_count":2},{"player_name":"Jeremy Pena","line_display":"2.5","sportsbook_count":1},{"player_name":"Jesus Sanchez","line_display":"To Hit HR","sportsbook_count":4},{"player_name":"Jesus Sanchez","line_display":"1.5","sportsbook_count":2},{"player_name":"Jesus Sanchez","line_display":"2.5","sportsbook_count":1},{"player_name":"Jose Altuve","line_display":"To Hit HR","sportsbook_count":4},{"player_name":"Jose Altuve","line_display":"1.5","sportsbook_count":2},{"player_name":"Jose Altuve","line_display":"2.5","sportsbook_count":1},{"player_name":"Mauricio Dubon","line_display":"To Hit HR","sportsbook_count":2},{"player_name":"Mauricio Dubon","line_display":"1.5","sportsbook_count":1},{"player_name":"Ramon Urias","line_display":"1.5","sportsbook_count":1},{"player_name":"Ramon Urias","line_display":"To Hit HR","sportsbook_count":2},{"player_name":"Ryan McMahon","line_display":"To Hit HR","sportsbook_count":3},{"player_name":"Ryan McMahon","line_display":"1.5","sportsbook_count":1},{"player_name":"Taylor Trammell","line_display":"To Hit HR","sportsbook_count":2},{"player_name":"Trent Grisham","line_display":"To Hit HR","sportsbook_count":4},{"player_name":"Trent Grisham","line_display":"1.5","sportsbook_count":2},{"player_name":"Trent Grisham","line_display":"2.5","sportsbook_count":1},{"player_name":"Yainer Diaz","line_display":"To Hit HR","sportsbook_count":4},{"player_name":"Yainer Diaz","line_display":"1.5","sportsbook_count":2},{"player_name":"Yainer Diaz","line_display":"2.5","sportsbook_count":1}]},{"game_id":"b690e27adc060a4a5a108914e25b181d","away_team":"Los Angeles Angels","home_team":"Detroit Tigers","commence_time":"2025-08-08T19:11:00-04:00","game_time_formatted":"07:11 PM EDT","player_count":48,"odds_status":"unknown","players":[{"player_name":"Bryce Teodosio","line_display":"To Hit HR","sportsbook_count":3},{"player_name":"Bryce Teodosio","line_display":"1.5","sportsbook_count":1},{"player_name":"Christian Moore","line_display":"To Hit HR","sportsbook_count":3},{"player_name":"Christian Moore","line_display":"1.5","sportsbook_count":1},{"player_name":"Colt Keith","line_display":"To Hit HR","sportsbook_count":4},{"player_name":"Colt Keith","line_display":"1.5","sportsbook_count":2},{"player_name":"Colt Keith","line_display":"2.5","sportsbook_count":1},{"player_name":"Dillon Dingler","line_display":"To Hit HR","sportsbook_count":3},{"player_name":"Dillon Dingler","line_display":"1.5","sportsbook_count":1},{"player_name":"Gleyber Torres","line_display":"To Hit HR","sportsbook_count":4},{"player_name":"Gleyber Torres","line_display":"1.5","sportsbook_count":2},{"player_name":"Gleyber Torres","line_display":"2.5","sportsbook_count":1},{"player_name":"Javier Baez","line_display":"To Hit HR","sportsbook_count":3},{"player_name":"Javier Baez","line_display":"1.5","sportsbook_count":1},{"player_name":"Jo Adell","line_display":"To Hit HR","sportsbook_count":4},{"player_name":"Jo Adell","line_display":"1.5","sportsbook_count":2},{"player_name":"Jo Adell","line_display":"2.5","sportsbook_count":1},{"player_name":"Kerry Carpenter","line_display":"To Hit HR","sportsbook_count":4},{"player_name":"Kerry Carpenter","line_display":"1.5","sportsbook_count":2},{"player_name":"Kerry Carpenter","line_display":"2.5","sportsbook_count":1},{"player_name":"Luis Rengifo","line_display":"To Hit HR","sportsbook_count":4},{"player_name":"Luis Rengifo","line_display":"1.5","sportsbook_count":2},{"player_name":"Mike Trout","line_display":"To Hit HR","sportsbook_count":4},{"player_name":"Mike Trout","line_display":"1.5","sportsbook_count":2},{"player_name":"Mike Trout","line_display":"2.5","sportsbook_count":1},{"player_name":"Nolan Schanuel","line_display":"To Hit HR","sportsbook_count":4},{"player_name":"Nolan Schanuel","line_display":"1.5","sportsbook_count":2},{"player_name":"Nolan Schanuel","line_display":"2.5","sportsbook_count":1},{"player_name":"Riley Greene","line_display":"To Hit HR","sportsbook_count":4},{"player_name":"Riley Greene","line_display":"1.5","sportsbook_count":2},{"player_name":"Riley Greene","line_display":"2.5","sportsbook_count":1},{"player_name":"Spencer Torkelson","line_display":"To Hit HR","sportsbook_count":4},{"player_name":"Spencer Torkelson","line_display":"1.5","sportsbook_count":2},{"player_name":"Spencer Torkelson","line_display":"2.5","sportsbook_count":1},{"player_name":"Taylor Ward","line_display":"To Hit HR","sportsbook_count":4},{"player_name":"Taylor Ward","line_display":"1.5","sportsbook_count":2},{"player_name":"Taylor Ward","line_display":"2.5","sportsbook_count":1},{"player_name":"Travis d'Arnaud","line_display":"To Hit HR","sportsbook_count":4},{"player_name":"Travis d'Arnaud","line_display":"1.5","sportsbook_count":2},{"player_name":"Travis d'Arnaud","line_display":"2.5","sportsbook_count":1},{"player_name":"Wenceel Perez","line_display":"To Hit HR","sportsbook_count":4},{"player_name":"Wenceel Perez","line_display":"1.5","sportsbook_count":2},{"player_name":"Zach McKinstry","line_display":"To Hit HR","sportsbook_count":4},{"player_name":"Zach McKinstry","line_display":"1.5","sportsbook_count":2},{"player_name":"Zach McKinstry","line_display":"2.5","sportsbook_count":1},{"player_name":"Zach Neto","line_display":"To Hit HR","sportsbook_count":4},{"player_name":"Zach Neto","line_display":"1.5","sportsbook_count":2},{"player_name":"Zach Neto","line_display":"2.5","sportsbook_count":1}]},{"game_id":"bebb519743a4daebbfa42d495e44e5ac","away_team":"Miami Marlins","home_team":"Atlanta Braves","commence_time":"2025-08-08T19:16:00-04:00","game_time_formatted":"07:16 PM EDT","player_count":49,"odds_status":"unknown","players":[{"player_name":"Agustín Ramírez","line_display":"To Hit HR","sportsbook_count":4},{"player_name":"Agustín Ramírez","line_display":"1.5","sportsbook_count":2},{"player_name":"Agustín Ramírez","line_display":"2.5","sportsbook_count":1},{"player_name":"Drake Baldwin","line_display":"To Hit HR","sportsbook_count":4},{"player_name":"Drake Baldwin","line_display":"1.5","sportsbook_count":2},{"player_name":"Drake Baldwin","line_display":"2.5","sportsbook_count":1},{"player_name":"Eli White","line_display":"To Hit HR","sportsbook_count":4},{"player_name":"Eli White","line_display":"1.5","sportsbook_count":2},{"player_name":"Graham Pauley","line_display":"To Hit HR","sportsbook_count":3},{"player_name":"Graham Pauley","line_display":"1.5","sportsbook_count":1},{"player_name":"Heriberto Hernandez","line_display":"To Hit HR","sportsbook_count":4},{"player_name":"Heriberto Hernandez","line_display":"1.5","sportsbook_count":2},{"player_name":"Heriberto Hernandez","line_display":"2.5","sportsbook_count":1},{"player_name":"Jakob Marsee","line_display":"To Hit HR","sportsbook_count":4},{"player_name":"Jakob Marsee","line_display":"1.5","sportsbook_count":2},{"player_name":"Jakob Marsee","line_display":"2.5","sportsbook_count":1},{"player_name":"Jurickson Profar","line_display":"To Hit HR","sportsbook_count":4},{"player_name":"Jurickson Profar","line_display":"1.5","sportsbook_count":2},{"player_name":"Jurickson Profar","line_display":"2.5","sportsbook_count":1},{"player_name":"Kyle Stowers","line_display":"To Hit HR","sportsbook_count":4},{"player_name":"Kyle Stowers","line_display":"1.5","sportsbook_count":2},{"player_name":"Kyle Stowers","line_display":"2.5","sportsbook_count":1},{"player_name":"Liam Hicks","line_display":"To Hit HR","sportsbook_count":4},{"player_name":"Liam Hicks","line_display":"1.5","sportsbook_count":2},{"player_name":"Liam Hicks","line_display":"2.5","sportsbook_count":1},{"player_name":"Matt Olson","line_display":"To Hit HR","sportsbook_count":4},{"player_name":"Matt Olson","line_display":"1.5","sportsbook_count":2},{"player_name":"Matt Olson","line_display":"2.5","sportsbook_count":1},{"player_name":"Michael Harris II","line_display":"To Hit HR","sportsbook_count":4},{"player_name":"Michael Harris II","line_display":"1.5","sportsbook_count":2},{"player_name":"Michael Harris II","line_display":"2.5","sportsbook_count":1},{"player_name":"Nacho Alvarez Jr.","line_display":"To Hit HR","sportsbook_count":3},{"player_name":"Nacho Alvarez Jr.","line_display":"1.5","sportsbook_count":1},{"player_name":"Nick Allen","line_display":"To Hit HR","sportsbook_count":3},{"player_name":"Nick Allen","line_display":"1.5","sportsbook_count":1},{"player_name":"Otto Lopez","line_display":"To Hit HR","sportsbook_count":4},{"player_name":"Otto Lopez","line_display":"1.5","sportsbook_count":2},{"player_name":"Otto Lopez","line_display":"2.5","sportsbook_count":1},{"player_name":"Ozzie Albies","line_display":"To Hit HR","sportsbook_count":4},{"player_name":"Ozzie Albies","line_display":"1.5","sportsbook_count":2},{"player_name":"Ozzie Albies","line_display":"2.5","sportsbook_count":1},{"player_name":"Sean Murphy","line_display":"To Hit HR","sportsbook_count":4},{"player_name":"Sean Murphy","line_display":"1.5","sportsbook_count":2},{"player_name":"Sean Murphy","line_display":"2.5","sportsbook_count":1},{"player_name":"Troy Johnston","line_display":"To Hit HR","sportsbook_count":3},{"player_name":"Troy Johnston","line_display":"1.5","sportsbook_count":1},{"player_name":"Xavier Edwards","line_display":"To Hit HR","sportsbook_count":4},{"player_name":"Xavier Edwards","line_display":"1.5","sportsbook_count":2},{"player_name":"Xavier Edwards","line_display":"2.5","sportsbook_count":1}]},{"game_id":"2180c892550d82cb5434ce13550f1e01","away_team":"Cleveland Guardians","home_team":"Chicago White Sox","commence_time":"2025-08-08T19:41:00-04:00","game_time_formatted":"07:41 PM EDT","player_count":54,"odds_status":"unknown","players":[{"player_name":"Andrew Benintendi","line_display":"To Hit HR","sportsbook_count":4},{"player_name":"Andrew Benintendi","line_display":"1.5","sportsbook_count":2},{"player_name":"Andrew Benintendi","line_display":"2.5","sportsbook_count":1},{"player_name":"Angel Martinez","line_display":"To Hit HR","sportsbook_count":1},{"player_name":"Angel Martinez","line_display":"1.5","sportsbook_count":1},{"player_name":"Bo Naylor","line_display":"To Hit HR","sportsbook_count":4},{"player_name":"Bo Naylor","line_display":"1.5","sportsbook_count":2},{"player_name":"Bo Naylor","line_display":"2.5","sportsbook_count":1},{"player_name":"Brayan Rocchio","line_display":"To Hit HR","sportsbook_count":3},{"player_name":"Brayan Rocchio","line_display":"1.5","sportsbook_count":1},{"player_name":"Brooks Baldwin","line_display":"To Hit HR","sportsbook_count":3},{"player_name":"Brooks Baldwin","line_display":"1.5","sportsbook_count":1},{"player_name":"C. J. Kayfus","line_display":"To Hit HR","sportsbook_count":3},{"player_name":"C. J. Kayfus","line_display":"1.5","sportsbook_count":1},{"player_name":"Carlos Santana","line_display":"To Hit HR","sportsbook_count":4},{"player_name":"Carlos Santana","line_display":"1.5","sportsbook_count":2},{"player_name":"Carlos Santana","line_display":"2.5","sportsbook_count":1},{"player_name":"Colson Montgomery","line_display":"To Hit HR","sportsbook_count":4},{"player_name":"Colson Montgomery","line_display":"1.5","sportsbook_count":2},{"player_name":"Colson Montgomery","line_display":"2.5","sportsbook_count":1},{"player_name":"Curtis Mead","line_display":"1.5","sportsbook_count":1},{"player_name":"Curtis Mead","line_display":"To Hit HR","sportsbook_count":1},{"player_name":"Daniel Schneemann","line_display":"To Hit HR","sportsbook_count":4},{"player_name":"Daniel Schneemann","line_display":"1.5","sportsbook_count":2},{"player_name":"Daniel Schneemann","line_display":"2.5","sportsbook_count":1},{"player_name":"Edgar Quero","line_display":"To Hit HR","sportsbook_count":4},{"player_name":"Edgar Quero","line_display":"1.5","sportsbook_count":2},{"player_name":"Edgar Quero","line_display":"2.5","sportsbook_count":1},{"player_name":"Gabriel Arias","line_display":"To Hit HR","sportsbook_count":4},{"player_name":"Gabriel Arias","line_display":"1.5","sportsbook_count":2},{"player_name":"Gabriel Arias","line_display":"2.5","sportsbook_count":1},{"player_name":"Jose Ramirez","line_display":"To Hit HR","sportsbook_count":4},{"player_name":"Jose Ramirez","line_display":"1.5","sportsbook_count":2},{"player_name":"Jose Ramirez","line_display":"2.5","sportsbook_count":1},{"player_name":"Josh Rojas","line_display":"To Hit HR","sportsbook_count":3},{"player_name":"Josh Rojas","line_display":"1.5","sportsbook_count":1},{"player_name":"Kyle Manzardo","line_display":"To Hit HR","sportsbook_count":4},{"player_name":"Kyle Manzardo","line_display":"1.5","sportsbook_count":2},{"player_name":"Kyle Manzardo","line_display":"2.5","sportsbook_count":1},{"player_name":"Kyle Teel","line_display":"To Hit HR","sportsbook_count":4},{"player_name":"Kyle Teel","line_display":"1.5","sportsbook_count":2},{"player_name":"Kyle Teel","line_display":"2.5","sportsbook_count":1},{"player_name":"Lenyn Sosa","line_display":"To Hit HR","sportsbook_count":4},{"player_name":"Lenyn Sosa","line_display":"1.5","sportsbook_count":2},{"player_name":"Lenyn Sosa","line_display":"2.5","sportsbook_count":1},{"player_name":"Luis Robert Jr.","line_display":"To Hit HR","sportsbook_count":4},{"player_name":"Luis Robert Jr.","line_display":"1.5","sportsbook_count":2},{"player_name":"Luis Robert Jr.","line_display":"2.5","sportsbook_count":1},{"player_name":"Mike Tauchman","line_display":"To Hit HR","sportsbook_count":4},{"player_name":"Mike Tauchman","line_display":"1.5","sportsbook_count":2},{"player_name":"Mike Tauchman","line_display":"2.5","sportsbook_count":1},{"player_name":"Steven Kwan","line_display":"To Hit HR","sportsbook_count":4},{"player_name":"Steven Kwan","line_display":"1.5","sportsbook_count":2},{"player_name":"Steven Kwan","line_display":"2.5","sportsbook_count":1}]},{"game_id":"3826008f0132082e1a3e4cce7e2f491f","away_team":"Philadelphia Phillies","home_team":"Texas Rangers","commence_time":"2025-08-08T20:06:00-04:00","game_time_formatted":"08:06 PM EDT","player_count":50,"odds_status":"unknown","players":[{"player_name":"Adolis Garcia","line_display":"To Hit HR","sportsbook_count":4},{"player_name":"Adolis Garcia","line_display":"1.5","sportsbook_count":2},{"player_name":"Adolis Garcia","line_display":"2.5","sportsbook_count":1},{"player_name":"Brandon Marsh","line_display":"To Hit HR","sportsbook_count":4},{"player_name":"Brandon Marsh","line_display":"1.5","sportsbook_count":2},{"player_name":"Brandon Marsh","line_display":"2.5","sportsbook_count":1},{"player_name":"Bryce Harper","line_display":"To Hit HR","sportsbook_count":4},{"player_name":"Bryce Harper","line_display":"1.5","sportsbook_count":2},{"player_name":"Bryce Harper","line_display":"2.5","sportsbook_count":1},{"player_name":"Bryson Stott","line_display":"To Hit HR","sportsbook_count":3},{"player_name":"Bryson Stott","line_display":"1.5","sportsbook_count":1},{"player_name":"Corey Seager","line_display":"To Hit HR","sportsbook_count":4},{"player_name":"Corey Seager","line_display":"1.5","sportsbook_count":2},{"player_name":"Corey Seager","line_display":"2.5","sportsbook_count":1},{"player_name":"Edmundo Sosa","line_display":"To Hit HR","sportsbook_count":3},{"player_name":"Edmundo Sosa","line_display":"1.5","sportsbook_count":1},{"player_name":"Ezequiel Duran","line_display":"To Hit HR","sportsbook_count":3},{"player_name":"Ezequiel Duran","line_display":"1.5","sportsbook_count":1},{"player_name":"J.T. Realmuto","line_display":"To Hit HR","sportsbook_count":4},{"player_name":"J.T. Realmuto","line_display":"1.5","sportsbook_count":2},{"player_name":"J.T. Realmuto","line_display":"2.5","sportsbook_count":1},{"player_name":"Jonah Heim","line_display":"To Hit HR","sportsbook_count":3},{"player_name":"Jonah Heim","line_display":"1.5","sportsbook_count":1},{"player_name":"Josh Jung","line_display":"To Hit HR","sportsbook_count":4},{"player_name":"Josh Jung","line_display":"1.5","sportsbook_count":2},{"player_name":"Josh Jung","line_display":"2.5","sportsbook_count":1},{"player_name":"Josh Smith","line_display":"To Hit HR","sportsbook_count":4},{"player_name":"Josh Smith","line_display":"1.5","sportsbook_count":2},{"player_name":"Josh Smith","line_display":"2.5","sportsbook_count":1},{"player_name":"Kyle Schwarber","line_display":"To Hit HR","sportsbook_count":4},{"player_name":"Kyle Schwarber","line_display":"1.5","sportsbook_count":2},{"player_name":"Kyle Schwarber","line_display":"2.5","sportsbook_count":1},{"player_name":"Marcus Semien","line_display":"To Hit HR","sportsbook_count":4},{"player_name":"Marcus Semien","line_display":"1.5","sportsbook_count":2},{"player_name":"Marcus Semien","line_display":"2.5","sportsbook_count":1},{"player_name":"Max Kepler","line_display":"To Hit HR","sportsbook_count":4},{"player_name":"Max Kepler","line_display":"1.5","sportsbook_count":2},{"player_name":"Max Kepler","line_display":"2.5","sportsbook_count":1},{"player_name":"Nick Castellanos","line_display":"To Hit HR","sportsbook_count":4},{"player_name":"Nick Castellanos","line_display":"1.5","sportsbook_count":2},{"player_name":"Nick Castellanos","line_display":"2.5","sportsbook_count":1},{"player_name":"Sam Haggerty","line_display":"To Hit HR","sportsbook_count":4},{"player_name":"Sam Haggerty","line_display":"1.5","sportsbook_count":2},{"player_name":"Sam Haggerty","line_display":"2.5","sportsbook_count":1},{"player_name":"Trea Turner","line_display":"To Hit HR","sportsbook_count":4},{"player_name":"Trea Turner","line_display":"1.5","sportsbook_count":2},{"player_name":"Trea Turner","line_display":"2.5","sportsbook_count":1},{"player_name":"Wyatt Langford","line_display":"To Hit HR","sportsbook_count":4},{"player_name":"Wyatt Langford","line_display":"1.5","sportsbook_count":2},{"player_name":"Wyatt Langford","line_display":"2.5","sportsbook_count":1}]},{"game_id":"8f7f05497ec6d9b2564b505b6f42d8c9","away_team":"Kansas City Royals","home_team":"Minnesota Twins","commence_time":"2025-08-08T20:11:00-04:00","game_time_formatted":"08:11 PM EDT","player_count":50,"odds_status":"unknown","players":[{"player_name":"Adam Frazier","line_display":"To Hit HR","sportsbook_count":4},{"player_name":"Adam Frazier","line_display":"1.5","sportsbook_count":2},{"player_name":"Adam Frazier","line_display":"2.5","sportsbook_count":1},{"player_name":"Austin Martin","line_display":"To Hit HR","sportsbook_count":4},{"player_name":"Austin Martin","line_display":"1.5","sportsbook_count":2},{"player_name":"Austin Martin","line_display":"2.5","sportsbook_count":1},{"player_name":"Bobby Witt Jr.","line_display":"To Hit HR","sportsbook_count":4},{"player_name":"Bobby Witt Jr.","line_display":"1.5","sportsbook_count":2},{"player_name":"Bobby Witt Jr.","line_display":"2.5","sportsbook_count":1},{"player_name":"Brooks Lee","line_display":"To Hit HR","sportsbook_count":4},{"player_name":"Brooks Lee","line_display":"1.5","sportsbook_count":2},{"player_name":"Brooks Lee","line_display":"2.5","sportsbook_count":1},{"player_name":"Christian Vazquez","line_display":"To Hit HR","sportsbook_count":3},{"player_name":"Christian Vazquez","line_display":"1.5","sportsbook_count":1},{"player_name":"John Rave","line_display":"To Hit HR","sportsbook_count":3},{"player_name":"John Rave","line_display":"1.5","sportsbook_count":1},{"player_name":"Jonathan India","line_display":"To Hit HR","sportsbook_count":4},{"player_name":"Jonathan India","line_display":"1.5","sportsbook_count":2},{"player_name":"Jonathan India","line_display":"2.5","sportsbook_count":1},{"player_name":"Kody Clemens","line_display":"To Hit HR","sportsbook_count":4},{"player_name":"Kody Clemens","line_display":"1.5","sportsbook_count":2},{"player_name":"Kody Clemens","line_display":"2.5","sportsbook_count":1},{"player_name":"Kyle Isbel","line_display":"To Hit HR","sportsbook_count":3},{"player_name":"Kyle Isbel","line_display":"1.5","sportsbook_count":1},{"player_name":"Luke Keaschall","line_display":"To Hit HR","sportsbook_count":4},{"player_name":"Luke Keaschall","line_display":"1.5","sportsbook_count":2},{"player_name":"Luke Keaschall","line_display":"2.5","sportsbook_count":1},{"player_name":"Maikel Garcia","line_display":"To Hit HR","sportsbook_count":4},{"player_name":"Maikel Garcia","line_display":"1.5","sportsbook_count":2},{"player_name":"Maikel Garcia","line_display":"2.5","sportsbook_count":1},{"player_name":"Matt Wallner","line_display":"To Hit HR","sportsbook_count":4},{"player_name":"Matt Wallner","line_display":"1.5","sportsbook_count":2},{"player_name":"Matt Wallner","line_display":"2.5","sportsbook_count":1},{"player_name":"Mike Yastrzemski","line_display":"To Hit HR","sportsbook_count":4},{"player_name":"Mike Yastrzemski","line_display":"1.5","sportsbook_count":2},{"player_name":"Mike Yastrzemski","line_display":"2.5","sportsbook_count":1},{"player_name":"Royce Lewis","line_display":"To Hit HR","sportsbook_count":4},{"player_name":"Royce Lewis","line_display":"1.5","sportsbook_count":2},{"player_name":"Royce Lewis","line_display":"2.5","sportsbook_count":1},{"player_name":"Ryan Jeffers","line_display":"To Hit HR","sportsbook_count":4},{"player_name":"Ryan Jeffers","line_display":"1.5","sportsbook_count":2},{"player_name":"Ryan Jeffers","line_display":"2.5","sportsbook_count":1},{"player_name":"Salvador Perez","line_display":"To Hit HR","sportsbook_count":4},{"player_name":"Salvador Perez","line_display":"1.5","sportsbook_count":2},{"player_name":"Salvador Perez","line_display":"2.5","sportsbook_count":1},{"player_name":"Trevor Larnach","line_display":"To Hit HR","sportsbook_count":3},{"player_name":"Trevor Larnach","line_display":"1.5","sportsbook_count":1},{"player_name":"Vinnie Pasquantino","line_display":"To Hit HR","sportsbook_count":4},{"player_name":"Vinnie Pasquantino","line_display":"1.5","sportsbook_count":2},{"player_name":"Vinnie Pasquantino","line_display":"2.5","sportsbook_count":1}]},{"game_id":"6d2eaf77812d46a4220449561fe1d30d","away_team":"New York Mets","home_team":"Milwaukee Brewers","commence_time":"2025-08-08T20:11:00-04:00","game_time_formatted":"08:11 PM EDT","player_count":49,"odds_status":"unknown","players":[{"player_name":"Andrew Vaughn","line_display":"To Hit HR","sportsbook_count":4},{"player_name":"Andrew Vaughn","line_display":"1.5","sportsbook_count":2},{"player_name":"Andrew Vaughn","line_display":"2.5","sportsbook_count":1},{"player_name":"Blake Perkins","line_display":"To Hit HR","sportsbook_count":3},{"player_name":"Blake Perkins","line_display":"1.5","sportsbook_count":1},{"player_name":"Brandon Nimmo","line_display":"To Hit HR","sportsbook_count":4},{"player_name":"Brandon Nimmo","line_display":"1.5","sportsbook_count":2},{"player_name":"Brandon Nimmo","line_display":"2.5","sportsbook_count":1},{"player_name":"Brice Turang","line_display":"To Hit HR","sportsbook_count":4},{"player_name":"Brice Turang","line_display":"1.5","sportsbook_count":2},{"player_name":"Brice Turang","line_display":"2.5","sportsbook_count":1},{"player_name":"Caleb Durbin","line_display":"To Hit HR","sportsbook_count":4},{"player_name":"Caleb Durbin","line_display":"1.5","sportsbook_count":2},{"player_name":"Cedric Mullins","line_display":"To Hit HR","sportsbook_count":4},{"player_name":"Cedric Mullins","line_display":"1.5","sportsbook_count":2},{"player_name":"Cedric Mullins","line_display":"2.5","sportsbook_count":1},{"player_name":"Christian Yelich","line_display":"To Hit HR","sportsbook_count":4},{"player_name":"Christian Yelich","line_display":"1.5","sportsbook_count":2},{"player_name":"Christian Yelich","line_display":"2.5","sportsbook_count":1},{"player_name":"Francisco Alvarez","line_display":"To Hit HR","sportsbook_count":3},{"player_name":"Francisco Alvarez","line_display":"1.5","sportsbook_count":1},{"player_name":"Francisco Lindor","line_display":"To Hit HR","sportsbook_count":4},{"player_name":"Francisco Lindor","line_display":"1.5","sportsbook_count":2},{"player_name":"Francisco Lindor","line_display":"2.5","sportsbook_count":1},{"player_name":"Isaac Collins","line_display":"To Hit HR","sportsbook_count":4},{"player_name":"Isaac Collins","line_display":"1.5","sportsbook_count":2},{"player_name":"Isaac Collins","line_display":"2.5","sportsbook_count":1},{"player_name":"Jeff McNeil","line_display":"To Hit HR","sportsbook_count":4},{"player_name":"Jeff McNeil","line_display":"1.5","sportsbook_count":2},{"player_name":"Jeff McNeil","line_display":"2.5","sportsbook_count":1},{"player_name":"Joey Ortiz","line_display":"To Hit HR","sportsbook_count":3},{"player_name":"Joey Ortiz","line_display":"1.5","sportsbook_count":1},{"player_name":"Juan Soto","line_display":"To Hit HR","sportsbook_count":4},{"player_name":"Juan Soto","line_display":"1.5","sportsbook_count":2},{"player_name":"Juan Soto","line_display":"2.5","sportsbook_count":1},{"player_name":"Mark Vientos","line_display":"To Hit HR","sportsbook_count":4},{"player_name":"Mark Vientos","line_display":"1.5","sportsbook_count":2},{"player_name":"Mark Vientos","line_display":"2.5","sportsbook_count":1},{"player_name":"Pete Alonso","line_display":"To Hit HR","sportsbook_count":4},{"player_name":"Pete Alonso","line_display":"1.5","sportsbook_count":2},{"player_name":"Pete Alonso","line_display":"2.5","sportsbook_count":1},{"player_name":"Ronny Mauricio","line_display":"To Hit HR","sportsbook_count":3},{"player_name":"Ronny Mauricio","line_display":"1.5","sportsbook_count":1},{"player_name":"Sal Frelick","line_display":"To Hit HR","sportsbook_count":4},{"player_name":"Sal Frelick","line_display":"1.5","sportsbook_count":2},{"player_name":"Sal Frelick","line_display":"2.5","sportsbook_count":1},{"player_name":"William Contreras","line_display":"To Hit HR","sportsbook_count":4},{"player_name":"William Contreras","line_display":"1.5","sportsbook_count":2},{"player_name":"William Contreras","line_display":"2.5","sportsbook_count":1}]},{"game_id":"dbf07eaf9f86c61fa7725cebb48145ca","away_team":"Chicago Cubs","home_team":"St. Louis Cardinals","commence_time":"2025-08-08T20:16:00-04:00","game_time_formatted":"08:16 PM EDT","player_count":50,"odds_status":"unknown","players":[{"player_name":"Alec Burleson","line_display":"To Hit HR","sportsbook_count":4},{"player_name":"Alec Burleson","line_display":"1.5","sportsbook_count":2},{"player_name":"Alec Burleson","line_display":"2.5","sportsbook_count":1},{"player_name":"Brendan Donovan","line_display":"To Hit HR","sportsbook_count":4},{"player_name":"Brendan Donovan","line_display":"1.5","sportsbook_count":2},{"player_name":"Brendan Donovan","line_display":"2.5","sportsbook_count":1},{"player_name":"Carson Kelly","line_display":"To Hit HR","sportsbook_count":4},{"player_name":"Carson Kelly","line_display":"1.5","sportsbook_count":2},{"player_name":"Carson Kelly","line_display":"2.5","sportsbook_count":1},{"player_name":"Dansby Swanson","line_display":"To Hit HR","sportsbook_count":4},{"player_name":"Dansby Swanson","line_display":"1.5","sportsbook_count":2},{"player_name":"Dansby Swanson","line_display":"2.5","sportsbook_count":1},{"player_name":"Ian Happ","line_display":"To Hit HR","sportsbook_count":4},{"player_name":"Ian Happ","line_display":"1.5","sportsbook_count":2},{"player_name":"Ian Happ","line_display":"2.5","sportsbook_count":1},{"player_name":"Ivan Herrera","line_display":"To Hit HR","sportsbook_count":4},{"player_name":"Ivan Herrera","line_display":"1.5","sportsbook_count":2},{"player_name":"Ivan Herrera","line_display":"2.5","sportsbook_count":1},{"player_name":"Jordan Walker","line_display":"To Hit HR","sportsbook_count":4},{"player_name":"Jordan Walker","line_display":"1.5","sportsbook_count":2},{"player_name":"Jordan Walker","line_display":"2.5","sportsbook_count":1},{"player_name":"Kyle Tucker","line_display":"To Hit HR","sportsbook_count":4},{"player_name":"Kyle Tucker","line_display":"1.5","sportsbook_count":2},{"player_name":"Kyle Tucker","line_display":"2.5","sportsbook_count":1},{"player_name":"Masyn Winn","line_display":"To Hit HR","sportsbook_count":4},{"player_name":"Masyn Winn","line_display":"1.5","sportsbook_count":2},{"player_name":"Masyn Winn","line_display":"2.5","sportsbook_count":1},{"player_name":"Matt Shaw","line_display":"To Hit HR","sportsbook_count":3},{"player_name":"Matt Shaw","line_display":"1.5","sportsbook_count":1},{"player_name":"Michael Busch","line_display":"To Hit HR","sportsbook_count":4},{"player_name":"Michael Busch","line_display":"1.5","sportsbook_count":2},{"player_name":"Michael Busch","line_display":"2.5","sportsbook_count":1},{"player_name":"Nico Hoerner","line_display":"To Hit HR","sportsbook_count":3},{"player_name":"Nico Hoerner","line_display":"1.5","sportsbook_count":1},{"player_name":"Pedro Pages","line_display":"To Hit HR","sportsbook_count":3},{"player_name":"Pedro Pages","line_display":"1.5","sportsbook_count":1},{"player_name":"Pete Crow-Armstrong","line_display":"To Hit HR","sportsbook_count":4},{"player_name":"Pete Crow-Armstrong","line_display":"1.5","sportsbook_count":2},{"player_name":"Pete Crow-Armstrong","line_display":"2.5","sportsbook_count":1},{"player_name":"Seiya Suzuki","line_display":"To Hit HR","sportsbook_count":4},{"player_name":"Seiya Suzuki","line_display":"1.5","sportsbook_count":2},{"player_name":"Seiya Suzuki","line_display":"2.5","sportsbook_count":1},{"player_name":"Thomas Saggese","line_display":"To Hit HR","sportsbook_count":4},{"player_name":"Thomas Saggese","line_display":"1.5","sportsbook_count":2},{"player_name":"Thomas Saggese","line_display":"2.5","sportsbook_count":1},{"player_name":"Victor Scott II","line_display":"To Hit HR","sportsbook_count":3},{"player_name":"Victor Scott II","line_display":"1.5","sportsbook_count":1},{"player_name":"Willson Contreras","line_display":"To Hit HR","sportsbook_count":4},{"player_name":"Willson Contreras","line_display":"1.5","sportsbook_count":2},{"player_name":"Willson Contreras","line_display":"2.5","sportsbook_count":1}]},{"game_id":"0e7099067d12b45f1913d5f14783a16f","away_team":"Colorado Rockies","home_team":"Arizona Diamondbacks","commence_time":"2025-08-08T21:41:00-04:00","game_time_formatted":"09:41 PM EDT","player_count":49,"odds_status":"unknown","players":[{"player_name":"Adael Amador","line_display":"To Hit HR","sportsbook_count":3},{"player_name":"Adael Amador","line_display":"1.5","sportsbook_count":1},{"player_name":"Alek Thomas","line_display":"To Hit HR","sportsbook_count":3},{"player_name":"Alek Thomas","line_display":"1.5","sportsbook_count":1},{"player_name":"Blaze Alexander","line_display":"To Hit HR","sportsbook_count":4},{"player_name":"Blaze Alexander","line_display":"1.5","sportsbook_count":2},{"player_name":"Blaze Alexander","line_display":"2.5","sportsbook_count":1},{"player_name":"Brenton Doyle","line_display":"To Hit HR","sportsbook_count":4},{"player_name":"Brenton Doyle","line_display":"1.5","sportsbook_count":2},{"player_name":"Brenton Doyle","line_display":"2.5","sportsbook_count":1},{"player_name":"Corbin Carroll","line_display":"To Hit HR","sportsbook_count":4},{"player_name":"Corbin Carroll","line_display":"1.5","sportsbook_count":2},{"player_name":"Corbin Carroll","line_display":"2.5","sportsbook_count":1},{"player_name":"Ezequiel Tovar","line_display":"To Hit HR","sportsbook_count":4},{"player_name":"Ezequiel Tovar","line_display":"1.5","sportsbook_count":2},{"player_name":"Ezequiel Tovar","line_display":"2.5","sportsbook_count":1},{"player_name":"Geraldo Perdomo","line_display":"To Hit HR","sportsbook_count":4},{"player_name":"Geraldo Perdomo","line_display":"1.5","sportsbook_count":2},{"player_name":"Hunter Goodman","line_display":"To Hit HR","sportsbook_count":4},{"player_name":"Hunter Goodman","line_display":"1.5","sportsbook_count":2},{"player_name":"Hunter Goodman","line_display":"2.5","sportsbook_count":1},{"player_name":"James McCann","line_display":"To Hit HR","sportsbook_count":4},{"player_name":"James McCann","line_display":"1.5","sportsbook_count":2},{"player_name":"James McCann","line_display":"2.5","sportsbook_count":1},{"player_name":"Jordan Beck","line_display":"To Hit HR","sportsbook_count":4},{"player_name":"Jordan Beck","line_display":"1.5","sportsbook_count":2},{"player_name":"Jordan Beck","line_display":"2.5","sportsbook_count":1},{"player_name":"Jorge Barrosa","line_display":"To Hit HR","sportsbook_count":3},{"player_name":"Jorge Barrosa","line_display":"1.5","sportsbook_count":1},{"player_name":"Ketel Marte","line_display":"To Hit HR","sportsbook_count":4},{"player_name":"Ketel Marte","line_display":"1.5","sportsbook_count":2},{"player_name":"Ketel Marte","line_display":"2.5","sportsbook_count":1},{"player_name":"Kyle Farmer","line_display":"To Hit HR","sportsbook_count":3},{"player_name":"Kyle Farmer","line_display":"1.5","sportsbook_count":1},{"player_name":"Lourdes Gurriel Jr.","line_display":"To Hit HR","sportsbook_count":4},{"player_name":"Lourdes Gurriel Jr.","line_display":"1.5","sportsbook_count":2},{"player_name":"Lourdes Gurriel Jr.","line_display":"2.5","sportsbook_count":1},{"player_name":"Mickey Moniak","line_display":"To Hit HR","sportsbook_count":4},{"player_name":"Mickey Moniak","line_display":"1.5","sportsbook_count":2},{"player_name":"Mickey Moniak","line_display":"2.5","sportsbook_count":1},{"player_name":"Tyler Freeman","line_display":"To Hit HR","sportsbook_count":4},{"player_name":"Tyler Freeman","line_display":"1.5","sportsbook_count":2},{"player_name":"Tyler Freeman","line_display":"2.5","sportsbook_count":1},{"player_name":"Tyler Locklear","line_display":"To Hit HR","sportsbook_count":4},{"player_name":"Tyler Locklear","line_display":"1.5","sportsbook_count":2},{"player_name":"Tyler Locklear","line_display":"2.5","sportsbook_count":1},{"player_name":"Warming Bernabel","line_display":"To Hit HR","sportsbook_count":4},{"player_name":"Warming Bernabel","line_display":"1.5","sportsbook_count":2},{"player_name":"Warming Bernabel","line_display":"2.5","sportsbook_count":1}]},{"game_id":"1cadb9abb78d3d219aec070df23a9fa3","away_team":"Boston Red Sox","home_team":"San Diego Padres","commence_time":"2025-08-08T21:41:00-04:00","game_time_formatted":"09:41 PM EDT","player_count":36,"odds_status":"unknown","players":[{"player_name":"Abraham Toro","line_display":"To Hit HR","sportsbook_count":3},{"player_name":"Abraham Toro","line_display":"1.5","sportsbook_count":1},{"player_name":"Alex Bregman","line_display":"To Hit HR","sportsbook_count":3},{"player_name":"Alex Bregman","line_display":"1.5","sportsbook_count":1},{"player_name":"Ceddanne Rafaela","line_display":"To Hit HR","sportsbook_count":3},{"player_name":"Ceddanne Rafaela","line_display":"1.5","sportsbook_count":1},{"player_name":"Connor Wong","line_display":"To Hit HR","sportsbook_count":3},{"player_name":"Connor Wong","line_display":"1.5","sportsbook_count":1},{"player_name":"Fernando Tatis Jr.","line_display":"To Hit HR","sportsbook_count":3},{"player_name":"Fernando Tatis Jr.","line_display":"1.5","sportsbook_count":1},{"player_name":"Freddy Fermin","line_display":"To Hit HR","sportsbook_count":3},{"player_name":"Freddy Fermin","line_display":"1.5","sportsbook_count":1},{"player_name":"Jackson Merrill","line_display":"To Hit HR","sportsbook_count":3},{"player_name":"Jackson Merrill","line_display":"1.5","sportsbook_count":1},{"player_name":"Jake Cronenworth","line_display":"To Hit HR","sportsbook_count":3},{"player_name":"Jake Cronenworth","line_display":"1.5","sportsbook_count":1},{"player_name":"Jarren Duran","line_display":"To Hit HR","sportsbook_count":3},{"player_name":"Jarren Duran","line_display":"1.5","sportsbook_count":1},{"player_name":"Luis Arraez","line_display":"To Hit HR","sportsbook_count":3},{"player_name":"Luis Arraez","line_display":"1.5","sportsbook_count":1},{"player_name":"Manny Machado","line_display":"To Hit HR","sportsbook_count":3},{"player_name":"Manny Machado","line_display":"1.5","sportsbook_count":1},{"player_name":"Masataka Yoshida","line_display":"To Hit HR","sportsbook_count":3},{"player_name":"Masataka Yoshida","line_display":"1.5","sportsbook_count":1},{"player_name":"Ramon Laureano","line_display":"To Hit HR","sportsbook_count":3},{"player_name":"Ramon Laureano","line_display":"1.5","sportsbook_count":1},{"player_name":"Roman Anthony","line_display":"To Hit HR","sportsbook_count":3},{"player_name":"Roman Anthony","line_display":"1.5","sportsbook_count":1},{"player_name":"Ryan O'Hearn","line_display":"To Hit HR","sportsbook_count":3},{"player_name":"Ryan O'Hearn","line_display":"1.5","sportsbook_count":1},{"player_name":"Trevor Story","line_display":"To Hit HR","sportsbook_count":3},{"player_name":"Trevor Story","line_display":"1.5","sportsbook_count":1},{"player_name":"Wilyer Abreu","line_display":"To Hit HR","sportsbook_count":3},{"player_name":"Wilyer Abreu","line_display":"1.5","sportsbook_count":1},{"player_name":"Xander Bogaerts","line_display":"To Hit HR","sportsbook_count":3},{"player_name":"Xander Bogaerts","line_display":"1.5","sportsbook_count":1}]},{"game_id":"1b8afa626c6916b9760d8316a9c86337","away_team":"Tampa Bay Rays","home_team":"Seattle Mariners","commence_time":"2025-08-08T21:41:00-04:00","game_time_formatted":"09:41 PM EDT","player_count":49,"odds_status":"unknown","players":[{"player_name":"Brandon Lowe","line_display":"To Hit HR","sportsbook_count":4},{"player_name":"Brandon Lowe","line_display":"1.5","sportsbook_count":2},{"player_name":"Brandon Lowe","line_display":"2.5","sportsbook_count":1},{"player_name":"Cal Raleigh","line_display":"To Hit HR","sportsbook_count":4},{"player_name":"Cal Raleigh","line_display":"1.5","sportsbook_count":2},{"player_name":"Cal Raleigh","line_display":"2.5","sportsbook_count":1},{"player_name":"Chandler Simpson","line_display":"To Hit HR","sportsbook_count":4},{"player_name":"Chandler Simpson","line_display":"1.5","sportsbook_count":2},{"player_name":"Chandler Simpson","line_display":"2.5","sportsbook_count":1},{"player_name":"Cole Young","line_display":"To Hit HR","sportsbook_count":3},{"player_name":"Cole Young","line_display":"1.5","sportsbook_count":1},{"player_name":"Dominic Canzone","line_display":"To Hit HR","sportsbook_count":4},{"player_name":"Dominic Canzone","line_display":"1.5","sportsbook_count":2},{"player_name":"Dominic Canzone","line_display":"2.5","sportsbook_count":1},{"player_name":"Donovan Solano","line_display":"To Hit HR","sportsbook_count":3},{"player_name":"Donovan Solano","line_display":"1.5","sportsbook_count":1},{"player_name":"Eugenio Suarez","line_display":"To Hit HR","sportsbook_count":4},{"player_name":"Eugenio Suarez","line_display":"1.5","sportsbook_count":2},{"player_name":"Eugenio Suarez","line_display":"2.5","sportsbook_count":1},{"player_name":"Ha-Seong Kim","line_display":"To Hit HR","sportsbook_count":4},{"player_name":"Ha-Seong Kim","line_display":"1.5","sportsbook_count":2},{"player_name":"Ha-Seong Kim","line_display":"2.5","sportsbook_count":1},{"player_name":"Hunter Feduccia","line_display":"To Hit HR","sportsbook_count":3},{"player_name":"Hunter Feduccia","line_display":"1.5","sportsbook_count":1},{"player_name":"J.P. Crawford","line_display":"To Hit HR","sportsbook_count":4},{"player_name":"J.P. Crawford","line_display":"1.5","sportsbook_count":2},{"player_name":"Jake Mangum","line_display":"To Hit HR","sportsbook_count":4},{"player_name":"Jake Mangum","line_display":"1.5","sportsbook_count":2},{"player_name":"Jake Mangum","line_display":"2.5","sportsbook_count":1},{"player_name":"Jorge Polanco","line_display":"To Hit HR","sportsbook_count":4},{"player_name":"Jorge Polanco","line_display":"1.5","sportsbook_count":2},{"player_name":"Jorge Polanco","line_display":"2.5","sportsbook_count":1},{"player_name":"Josh Lowe","line_display":"To Hit HR","sportsbook_count":4},{"player_name":"Josh Lowe","line_display":"1.5","sportsbook_count":2},{"player_name":"Josh Lowe","line_display":"2.5","sportsbook_count":1},{"player_name":"Julio Rodriguez","line_display":"To Hit HR","sportsbook_count":4},{"player_name":"Julio Rodriguez","line_display":"1.5","sportsbook_count":2},{"player_name":"Julio Rodriguez","line_display":"2.5","sportsbook_count":1},{"player_name":"Junior Caminero","line_display":"To Hit HR","sportsbook_count":4},{"player_name":"Junior Caminero","line_display":"1.5","sportsbook_count":2},{"player_name":"Junior Caminero","line_display":"2.5","sportsbook_count":1},{"player_name":"Randy Arozarena","line_display":"To Hit HR","sportsbook_count":4},{"player_name":"Randy Arozarena","line_display":"1.5","sportsbook_count":2},{"player_name":"Randy Arozarena","line_display":"2.5","sportsbook_count":1},{"player_name":"Taylor Walls","line_display":"To Hit HR","sportsbook_count":3},{"player_name":"Taylor Walls","line_display":"1.5","sportsbook_count":1},{"player_name":"Yandy Diaz","line_display":"To Hit HR","sportsbook_count":4},{"player_name":"Yandy Diaz","line_display":"1.5","sportsbook_count":2},{"player_name":"Yandy Diaz","line_display":"2.5","sportsbook_count":1}]},{"game_id":"176aede68466c300af2b41dfabb70b34","away_team":"Toronto Blue Jays","home_team":"Los Angeles Dodgers","commence_time":"2025-08-08T22:11:00-04:00","game_time_formatted":"10:11 PM EDT","player_count":54,"odds_status":"unknown","players":[{"player_name":"Addison Barger","line_display":"To Hit HR","sportsbook_count":4},{"player_name":"Addison Barger","line_display":"1.5","sportsbook_count":2},{"player_name":"Addison Barger","line_display":"2.5","sportsbook_count":1},{"player_name":"Alejandro Kirk","line_display":"To Hit HR","sportsbook_count":4},{"player_name":"Alejandro Kirk","line_display":"1.5","sportsbook_count":2},{"player_name":"Alejandro Kirk","line_display":"2.5","sportsbook_count":1},{"player_name":"Alex Freeland","line_display":"1.5","sportsbook_count":1},{"player_name":"Alex Freeland","line_display":"To Hit HR","sportsbook_count":2},{"player_name":"Andy Pages","line_display":"To Hit HR","sportsbook_count":3},{"player_name":"Andy Pages","line_display":"1.5","sportsbook_count":1},{"player_name":"Bo Bichette","line_display":"To Hit HR","sportsbook_count":4},{"player_name":"Bo Bichette","line_display":"1.5","sportsbook_count":2},{"player_name":"Bo Bichette","line_display":"2.5","sportsbook_count":1},{"player_name":"Buddy Kennedy","line_display":"To Hit HR","sportsbook_count":2},{"player_name":"Buddy Kennedy","line_display":"1.5","sportsbook_count":1},{"player_name":"Davis Schneider","line_display":"To Hit HR","sportsbook_count":4},{"player_name":"Davis Schneider","line_display":"1.5","sportsbook_count":2},{"player_name":"Davis Schneider","line_display":"2.5","sportsbook_count":1},{"player_name":"Ernie Clement","line_display":"To Hit HR","sportsbook_count":4},{"player_name":"Ernie Clement","line_display":"1.5","sportsbook_count":2},{"player_name":"Ernie Clement","line_display":"2.5","sportsbook_count":1},{"player_name":"Freddie Freeman","line_display":"To Hit HR","sportsbook_count":4},{"player_name":"Freddie Freeman","line_display":"1.5","sportsbook_count":2},{"player_name":"Freddie Freeman","line_display":"2.5","sportsbook_count":1},{"player_name":"Max Muncy","line_display":"To Hit HR","sportsbook_count":4},{"player_name":"Max Muncy","line_display":"1.5","sportsbook_count":2},{"player_name":"Max Muncy","line_display":"2.5","sportsbook_count":1},{"player_name":"Michael Conforto","line_display":"To Hit HR","sportsbook_count":4},{"player_name":"Michael Conforto","line_display":"1.5","sportsbook_count":2},{"player_name":"Michael Conforto","line_display":"2.5","sportsbook_count":1},{"player_name":"Miguel Rojas","line_display":"To Hit HR","sportsbook_count":2},{"player_name":"Miguel Rojas","line_display":"1.5","sportsbook_count":1},{"player_name":"Mookie Betts","line_display":"To Hit HR","sportsbook_count":4},{"player_name":"Mookie Betts","line_display":"1.5","sportsbook_count":2},{"player_name":"Mookie Betts","line_display":"2.5","sportsbook_count":1},{"player_name":"Myles Straw","line_display":"To Hit HR","sportsbook_count":3},{"player_name":"Myles Straw","line_display":"1.5","sportsbook_count":1},{"player_name":"Nathan Lukes","line_display":"To Hit HR","sportsbook_count":2},{"player_name":"Nathan Lukes","line_display":"1.5","sportsbook_count":1},{"player_name":"Shohei Ohtani","line_display":"To Hit HR","sportsbook_count":4},{"player_name":"Shohei Ohtani","line_display":"1.5","sportsbook_count":2},{"player_name":"Shohei Ohtani","line_display":"2.5","sportsbook_count":1},{"player_name":"Teoscar Hernandez","line_display":"To Hit HR","sportsbook_count":3},{"player_name":"Teoscar Hernandez","line_display":"1.5","sportsbook_count":1},{"player_name":"Teoscar Hernandez","line_display":"2.5","sportsbook_count":1},{"player_name":"Ty France","line_display":"To Hit HR","sportsbook_count":4},{"player_name":"Ty France","line_display":"1.5","sportsbook_count":2},{"player_name":"Ty France","line_display":"2.5","sportsbook_count":1},{"player_name":"Vladimir Guerrero Jr.","line_display":"To Hit HR","sportsbook_count":4},{"player_name":"Vladimir Guerrero Jr.","line_display":"1.5","sportsbook_count":2},{"player_name":"Vladimir Guerrero Jr.","line_display":"2.5","sportsbook_count":1},{"player_name":"Will Smith","line_display":"To Hit HR","sportsbook_count":4},{"player_name":"Will Smith","line_display":"1.5","sportsbook_count":2},{"player_name":"Will Smith","line_display":"2.5","sportsbook_count":1}]},{"game_id":"1f0e492ec6029adec7b2dd2f9c4617e6","away_team":"Washington Nationals","home_team":"San Francisco Giants","commence_time":"2025-08-08T22:16:00-04:00","game_time_formatted":"10:16 PM EDT","player_count":21,"odds_status":"unknown","players":[{"player_name":"Casey Schmitt","line_display":"1.5","sportsbook_count":1},{"player_name":"Casey Schmitt","line_display":"2.5","sportsbook_count":1},{"player_name":"Casey Schmitt","line_display":"To Hit HR","sportsbook_count":1},{"player_name":"Dominic Smith","line_display":"2.5","sportsbook_count":1},{"player_name":"Dominic Smith","line_display":"1.5","sportsbook_count":1},{"player_name":"Dominic Smith","line_display":"To Hit HR","sportsbook_count":1},{"player_name":"Heliot Ramos","line_display":"2.5","sportsbook_count":1},{"player_name":"Heliot Ramos","line_display":"1.5","sportsbook_count":1},{"player_name":"Heliot Ramos","line_display":"To Hit HR","sportsbook_count":1},{"player_name":"Jung Hoo Lee","line_display":"1.5","sportsbook_count":1},{"player_name":"Jung Hoo Lee","line_display":"2.5","sportsbook_count":1},{"player_name":"Jung Hoo Lee","line_display":"To Hit HR","sportsbook_count":1},{"player_name":"Matt Chapman","line_display":"1.5","sportsbook_count":1},{"player_name":"Matt Chapman","line_display":"2.5","sportsbook_count":1},{"player_name":"Matt Chapman","line_display":"To Hit HR","sportsbook_count":1},{"player_name":"Rafael Devers","line_display":"2.5","sportsbook_count":1},{"player_name":"Rafael Devers","line_display":"1.5","sportsbook_count":1},{"player_name":"Rafael Devers","line_display":"To Hit HR","sportsbook_count":1},{"player_name":"Willy Adames","line_display":"1.5","sportsbook_count":1},{"player_name":"Willy Adames","line_display":"2.5","sportsbook_count":1},{"player_name":"Willy Adames","line_display":"To Hit HR","sportsbook_count":1}]}]}