{"metadata":{"generated_at":"2025-09-30T21:48:25.768923-04:00","date":"2025-09-30","timezone":"US/Eastern","sport":"baseball_mlb","market":"batter_home_runs","format":"summary","description":"Lightweight summary with game info and player counts","use_case":"Quick overview, mobile apps, initial page loads"},"summary":{"total_games":1,"games_with_props":1,"total_players":44},"games":[{"game_id":"c39a10188098658e3f02a8bdec57655a","away_team":"Cincinnati Reds","home_team":"Los Angeles Dodgers","commence_time":"2025-09-30T21:08:24-04:00","game_time_formatted":"09:08 PM EDT","player_count":44,"odds_status":"unknown","players":[{"player_name":"Andy Pages","line_display":"To Hit HR","sportsbook_count":2},{"player_name":"Andy Pages","line_display":"1.5","sportsbook_count":2},{"player_name":"Austin Hays","line_display":"To Hit HR","sportsbook_count":2},{"player_name":"Austin Hays","line_display":"2.5","sportsbook_count":1},{"player_name":"Austin Hays","line_display":"1.5","sportsbook_count":1},{"player_name":"Ben Rortvedt","line_display":"To Hit HR","sportsbook_count":2},{"player_name":"Ben Rortvedt","line_display":"1.5","sportsbook_count":1},{"player_name":"Elly De La Cruz","line_display":"To Hit HR","sportsbook_count":2},{"player_name":"Elly De La Cruz","line_display":"1.5","sportsbook_count":2},{"player_name":"Elly De La Cruz","line_display":"2.5","sportsbook_count":1},{"player_name":"Enrique Hernandez","line_display":"To Hit HR","sportsbook_count":2},{"player_name":"Enrique Hernandez","line_display":"2.5","sportsbook_count":1},{"player_name":"Enrique Hernandez","line_display":"1.5","sportsbook_count":1},{"player_name":"Freddie Freeman","line_display":"To Hit HR","sportsbook_count":2},{"player_name":"Freddie Freeman","line_display":"1.5","sportsbook_count":2},{"player_name":"Freddie Freeman","line_display":"2.5","sportsbook_count":1},{"player_name":"Ke'Bryan Hayes","line_display":"To Hit HR","sportsbook_count":2},{"player_name":"Ke'Bryan Hayes","line_display":"1.5","sportsbook_count":1},{"player_name":"Matt McLain","line_display":"To Hit HR","sportsbook_count":2},{"player_name":"Matt McLain","line_display":"1.5","sportsbook_count":2},{"player_name":"Max Muncy","line_display":"To Hit HR","sportsbook_count":2},{"player_name":"Max Muncy","line_display":"1.5","sportsbook_count":2},{"player_name":"Max Muncy","line_display":"2.5","sportsbook_count":1},{"player_name":"Miguel Andujar","line_display":"To Hit HR","sportsbook_count":2},{"player_name":"Miguel Andujar","line_display":"1.5","sportsbook_count":1},{"player_name":"Mookie Betts","line_display":"1.5","sportsbook_count":1},{"player_name":"Mookie Betts","line_display":"2.5","sportsbook_count":1},{"player_name":"Mookie Betts","line_display":"To Hit HR","sportsbook_count":1},{"player_name":"Noelvi Marte","line_display":"To Hit HR","sportsbook_count":2},{"player_name":"Noelvi Marte","line_display":"1.5","sportsbook_count":1},{"player_name":"Noelvi Marte","line_display":"2.5","sportsbook_count":1},{"player_name":"Shohei Ohtani","line_display":"1.5","sportsbook_count":2},{"player_name":"Shohei Ohtani","line_display":"2.5","sportsbook_count":1},{"player_name":"Spencer Steer","line_display":"To Hit HR","sportsbook_count":2},{"player_name":"Spencer Steer","line_display":"1.5","sportsbook_count":1},{"player_name":"TJ Friedl","line_display":"To Hit HR","sportsbook_count":2},{"player_name":"TJ Friedl","line_display":"1.5","sportsbook_count":1},{"player_name":"Teoscar Hernandez","line_display":"To Hit HR","sportsbook_count":2},{"player_name":"Teoscar Hernandez","line_display":"1.5","sportsbook_count":2},{"player_name":"Tommy Edman","line_display":"To Hit HR","sportsbook_count":2},{"player_name":"Tommy Edman","line_display":"1.5","sportsbook_count":2},{"player_name":"Tyler Stephenson","line_display":"To Hit HR","sportsbook_count":2},{"player_name":"Tyler Stephenson","line_display":"1.5","sportsbook_count":1},{"player_name":"Tyler Stephenson","line_display":"2.5","sportsbook_count":1}]}]}